LICENSE
psgnuitka.py
README.md
psgnuitka-0.2.8.dist-info/LICENSE
psgnuitka-0.2.8.dist-info/METADATA
psgnuitka-0.2.8.dist-info/WHEEL
psgnuitka-0.2.8.dist-info/RECORD
