Metadata-Version: 2.1
Name: psgnuitka
Version: 0.2.8
Summary: A graphical tool to facilitate the generation of Python executables using Nuitka
Home-page: https://github.com/BoulderH/psgnuitka
License: MIT
Keywords: nuitka,PySimpleGUI,psgnuitka
Author: boulderh
Author-email: boulderh@163.com
Requires-Python: >=3.8,<4.0
Classifier: License :: OSI Approved :: MIT License
Classifier: Programming Language :: Python :: 3
Classifier: Programming Language :: Python :: 3.8
Classifier: Programming Language :: Python :: 3.9
Classifier: Programming Language :: Python :: 3.10
Classifier: Programming Language :: Python :: 3.11
Requires-Dist: pysimplegui (>=4.60.0,<5.0.0)
Project-URL: Repository, https://github.com/BoulderH/psgnuitka
